setup.cfg
setup.py
tw/__init__.py
tw.prototype.egg-info/PKG-INFO
tw.prototype.egg-info/SOURCES.txt
tw.prototype.egg-info/dependency_links.txt
tw.prototype.egg-info/entry_points.txt
tw.prototype.egg-info/namespace_packages.txt
tw.prototype.egg-info/not-zip-safe
tw.prototype.egg-info/requires.txt
tw.prototype.egg-info/top_level.txt
tw/prototype/__init__.py
tw/prototype/activeform.py
tw/prototype/js.py
tw/prototype/release.py
tw/prototype/samples.py
tw/prototype/widgets.py
tw/prototype/examples/__init__.py
tw/prototype/examples/tg2/__init__.py
tw/prototype/examples/tg2/browser.py
tw/prototype/frameworks/__init__.py
tw/prototype/frameworks/tg2/__init__.py
tw/prototype/frameworks/tg2/activeform.py
tw/prototype/templates/__init__.py